OptimalBragg/__init__.py
OptimalBragg/analysis.py
OptimalBragg/costs.py
OptimalBragg/layers.py
OptimalBragg/materials.py
OptimalBragg/noise.py
OptimalBragg/optimizer.py
OptimalBragg/plot.py
OptimalBragg-1.0.2.dist-info/LICENSE
OptimalBragg-1.0.2.dist-info/METADATA
OptimalBragg-1.0.2.dist-info/WHEEL
OptimalBragg-1.0.2.dist-info/top_level.txt
OptimalBragg-1.0.2.dist-info/RECORD
