Metadata-Version: 2.1
Name: OptimalBragg
Version: 1.0.2
Summary: Package for the design and optimization of dielectric coatings
Home-page: https://github.com/CaltechExperimentalGravity/OptimalBragg/
Author: CaltechExperimentalGravity
Author-email: pacosalces@gmail.com
License: LICENSE
Classifier: Programming Language :: Python :: 3
Classifier: License :: OSI Approved :: BSD License
Classifier: Operating System :: OS Independent
Requires-Python: >=3.10
License-File: LICENSE
Requires-Dist: numpy
Requires-Dist: scipy
Requires-Dist: matplotlib
Requires-Dist: h5py
Requires-Dist: pyyaml
Requires-Dist: physunits
Requires-Dist: corner
Requires-Dist: emcee
